tests/__init__.py
vni/__init__.py
vni/usage_vni.py
vni/utils.py
vni/base/__init__.py
vni/base/estimator.py
vni/non_parametric_estimators/__init__.py
vni/non_parametric_estimators/kde.py
vni/non_parametric_estimators/kde_copy.py
vni/parametric_estimators/__init__.py
vni/parametric_estimators/mean_covariance.py
vni-0.1.0.dist-info/LICENSE
vni-0.1.0.dist-info/METADATA
vni-0.1.0.dist-info/WHEEL
vni-0.1.0.dist-info/top_level.txt
vni-0.1.0.dist-info/RECORD
