Metadata-Version: 2.1
Name: vni
Version: 0.1.0
Summary: Vectorized Numerical Intervention
Home-page: https://github.com/Giovannibriglia/VectorizedNumericalIntervention
Author: Giovanni Briglia
Author-email: giovanni.briglia@unimore.it
License: GPLv3
License-File: LICENSE
Requires-Dist: torch
